{
  "crawlDate": "2026-04-12",
  "crawlTime": "2026-04-12T01:52:38.674Z",
  "teams": {
    "samsung": {
      "teamKR": "삼성",
      "g": 12,
      "w": 7,
      "l": 4,
      "t": 1,
      "pct": 0.636,
      "rs": 66,
      "ra": 83,
      "runDiff": -17,
      "runDiffPerGame": -1.42,
      "last10raw": "7승1무2패",
      "last10pct": 0.778,
      "streakRaw": "2승",
      "streak": 2
    },
    "kia": {
      "teamKR": "KIA",
      "g": 12,
      "w": 5,
      "l": 7,
      "t": 0,
      "pct": 0.417,
      "rs": 57,
      "ra": 74,
      "runDiff": -17,
      "runDiffPerGame": -1.42,
      "last10raw": "5승0무5패",
      "last10pct": 0.5,
      "streakRaw": "3승",
      "streak": 3
    },
    "lg": {
      "teamKR": "LG",
      "g": 12,
      "w": 8,
      "l": 4,
      "t": 0,
      "pct": 0.667,
      "rs": 58,
      "ra": 90,
      "runDiff": -32,
      "runDiffPerGame": -2.67,
      "last10raw": "8승0무2패",
      "last10pct": 0.8,
      "streakRaw": "6승",
      "streak": 6
    },
    "doosan": {
      "teamKR": "두산",
      "g": 12,
      "w": 4,
      "l": 7,
      "t": 1,
      "pct": 0.364,
      "rs": 57,
      "ra": 107,
      "runDiff": -50,
      "runDiffPerGame": -4.17,
      "last10raw": "3승1무6패",
      "last10pct": 0.333,
      "streakRaw": "1패",
      "streak": -1
    },
    "kt": {
      "teamKR": "KT",
      "g": 12,
      "w": 8,
      "l": 4,
      "t": 0,
      "pct": 0.667,
      "rs": 83,
      "ra": 103,
      "runDiff": -20,
      "runDiffPerGame": -1.67,
      "last10raw": "6승0무4패",
      "last10pct": 0.6,
      "streakRaw": "1승",
      "streak": 1
    },
    "ssg": {
      "teamKR": "SSG",
      "g": 12,
      "w": 7,
      "l": 5,
      "t": 0,
      "pct": 0.583,
      "rs": 78,
      "ra": 92,
      "runDiff": -14,
      "runDiffPerGame": -1.17,
      "last10raw": "5승0무5패",
      "last10pct": 0.5,
      "streakRaw": "4패",
      "streak": -4
    },
    "hanwha": {
      "teamKR": "한화",
      "g": 12,
      "w": 6,
      "l": 6,
      "t": 0,
      "pct": 0.5,
      "rs": 83,
      "ra": 111,
      "runDiff": -28,
      "runDiffPerGame": -2.33,
      "last10raw": "4승0무6패",
      "last10pct": 0.4,
      "streakRaw": "2패",
      "streak": -2
    },
    "lotte": {
      "teamKR": "롯데",
      "g": 12,
      "w": 5,
      "l": 7,
      "t": 0,
      "pct": 0.417,
      "rs": 48,
      "ra": 97,
      "runDiff": -49,
      "runDiffPerGame": -4.08,
      "last10raw": "3승0무7패",
      "last10pct": 0.3,
      "streakRaw": "3승",
      "streak": 3
    },
    "nc": {
      "teamKR": "NC",
      "g": 12,
      "w": 6,
      "l": 6,
      "t": 0,
      "pct": 0.5,
      "rs": 58,
      "ra": 79,
      "runDiff": -21,
      "runDiffPerGame": -1.75,
      "last10raw": "5승0무5패",
      "last10pct": 0.5,
      "streakRaw": "5패",
      "streak": -5
    },
    "kiwoom": {
      "teamKR": "키움",
      "g": 12,
      "w": 3,
      "l": 9,
      "t": 0,
      "pct": 0.25,
      "rs": 52,
      "ra": 86,
      "runDiff": -34,
      "runDiffPerGame": -2.83,
      "last10raw": "3승0무7패",
      "last10pct": 0.3,
      "streakRaw": "3패",
      "streak": -3
    }
  }
}